detectlanguage/__init__.py
detectlanguage/api.py
detectlanguage/client.py
detectlanguage/configuration.py
detectlanguage/exceptions.py
detectlanguage-2.0.0.dist-info/licenses/LICENSE
detectlanguage-2.0.0.dist-info/METADATA
detectlanguage-2.0.0.dist-info/WHEEL
detectlanguage-2.0.0.dist-info/top_level.txt
detectlanguage-2.0.0.dist-info/RECORD
