Metadata-Version: 2.4
Name: detectlanguage
Version: 2.0.0
Summary: Language Detection API Client
Home-page: https://github.com/detectlanguage/detectlanguage-python
Download-URL: https://github.com/detectlanguage/detectlanguage-python
Author: Laurynas Butkus
Author-email: info@detectlanguage.com
License: MIT
Keywords: language,identification,detection,api,client
License-File: LICENSE
Requires-Dist: requests>=2.4.2
Dynamic: author
Dynamic: author-email
Dynamic: description
Dynamic: description-content-type
Dynamic: download-url
Dynamic: home-page
Dynamic: keywords
Dynamic: license
Dynamic: license-file
Dynamic: requires-dist
Dynamic: summary
